ICQBot/ICQBot.py
ICQBot/__init__.py
ICQBot/dispatcher/__init__.py
ICQBot/dispatcher/dispatcher.py
ICQBot/dispatcher/filters.py
ICQBot/dispatcher/handlers.py
ICQBot/exceptions/ClientErrors.py
ICQBot/exceptions/DispatcherErrors.py
ICQBot/exceptions/GenericErrors.py
ICQBot/exceptions/GroupErrors.py
ICQBot/exceptions/MessageErrors.py
ICQBot/exceptions/ServerErrors.py
ICQBot/exceptions/__init__.py
ICQBot/ext/Keyboards.py
ICQBot/ext/__init__.py
ICQBot/ext/parseModes.py
ICQBot/ext/util.py
ICQBot/mapper/ChatMapper.py
ICQBot/mapper/EventsMapper.py
ICQBot/mapper/MessagesMapper.py
ICQBot/mapper/__init__.py
ICQBot/messages/__init__.py
ICQBot/messages/callback.py
ICQBot/messages/message.py
ICQBot/messages/payloads.py
ICQBot-0.2.3b0.dist-info/LICENSE
ICQBot-0.2.3b0.dist-info/METADATA
ICQBot-0.2.3b0.dist-info/WHEEL
ICQBot-0.2.3b0.dist-info/top_level.txt
ICQBot-0.2.3b0.dist-info/RECORD
