Metadata-Version: 2.1
Name: ICQBot
Version: 0.2.3b0
Home-page: https://github.com/kamuridesu/ICQBotPy
Download-URL: https://github.com/kamuridesu/ICQBotPy/archive/refs/heads/main.zip
Author: Kamuri Amorim
Author-email: luiz.k.amorim@gmail.com
License: MIT
License-File: LICENSE
Requires-Dist: aiohttp (==3.8.1)
